scanRBP/__init__.py
scanRBP/scanRBP
scanRBP/scanRBP.config.example
scanRBP/version
scanRBP/config/__init__.py
scanRBP/database/__init__.py
scanRBP/pwm/__init__.py
scanRBP-0.3.data/scripts/scanRBP
scanRBP-0.3.dist-info/METADATA
scanRBP-0.3.dist-info/WHEEL
scanRBP-0.3.dist-info/top_level.txt
scanRBP-0.3.dist-info/RECORD
