Metadata-Version: 2.2
Name: scanRBP
Version: 0.3
Summary: scanRBP: RNA-protein binding toolkit
Home-page: https://github.com/grexor/scanRBP
Author: Gregor Rot
Author-email: gregor.rot@gmail.com
Keywords: scanRBP,bioinformatics,RBP,RNA-protein binding,toolkit
Classifier: Programming Language :: Python :: 3
Requires-Dist: scipy
Requires-Dist: biopython
Requires-Dist: seaborn
Requires-Dist: matplotlib
Requires-Dist: pybio
Dynamic: author
Dynamic: author-email
Dynamic: classifier
Dynamic: description
Dynamic: description-content-type
Dynamic: home-page
Dynamic: keywords
Dynamic: requires-dist
Dynamic: summary
